Workbook

Sheet product price list
A1: Product Name | B1: Buying price (Rupees) | C1: Profit margin(%) | D1: Selling price | E1: GST(%) | F1: FINAL PRICE
A2: Floor cleaner | B2: 313 | C2: 50 | D2: =B2*(1+(C2/100)) -> 469.5 | E2: 18 | F2: =D2*(1+(E2/100)) -> 554.01
A3: bleaching powder | B3: 193 | C3: 50 | D3: =B3*(1+(C3/100)) -> 289.5 | E3: 18 | F3: =D3*(1+(E3/100)) -> 341.61
A4: glass cleaner | B4: 162 | C4: 50 | D4: =B4*(1+(C4/100)) -> 243 | E4: 18 | F4: =D4*(1+(E4/100)) -> 286.74
A5: Naoh | B5: 401 | C5: 50 | D5: =B5*(1+(C5/100)) -> 601.5 | E5: 18 | F5: =D5*(1+(E5/100)) -> 709.77
A6: sodium hypochloride | B6: 110 | C6: 50 | D6: =B6*(1+(C6/100)) -> 165 | E6: 18 | F6: =D6*(1+(E6/100)) -> 194.7
A7: handwash | B7: 401 | C7: 50 | D7: =B7*(1+(C7/100)) -> 601.5 | E7: 18 | F7: =D7*(1+(E7/100)) -> 709.77
A8: room freshner | B8: 374 | C8: 50 | D8: =B8*(1+(C8/100)) -> 561 | E8: 18 | F8: =D8*(1+(E8/100)) -> 661.98
A9: sanitary cubes | B9: 249 | C9: 50 | D9: =B9*(1+(C9/100)) -> 373.5 | E9: 18 | F9: =D9*(1+(E9/100)) -> 440.73
A10: napthalene balls | B10: 317 | C10: 50 | D10: =B10*(1+(C10/100)) -> 475.5 | E10: 18 | F10: =D10*(1+(E10/100)) -> 561.09
A11: tissue packs | B11: 490 | C11: 50 | D11: =B11*(1+(C11/100)) -> 735 | E11: 18 | F11: =D11*(1+(E11/100)) -> 867.3
A12: napkins | B12: 209 | C12: 50 | D12: =B12*(1+(C12/100)) -> 313.5 | E12: 18 | F12: =D12*(1+(E12/100)) -> 369.93
A13: mop | B13: 485 | C13: 50 | D13: =B13*(1+(C13/100)) -> 727.5 | E13: 18 | F13: =D13*(1+(E13/100)) -> 858.45
... A20: detergent | B20: 421 | C20: 50 | D20: =B20*(1+(C20/100)) -> 631.5 | E20: 18 | F20: =D20*(1+(E20/100)) -> 745.17

Sheet DAILY SALES ENTRY
A1: DATE | B1: PRODUCT NAME | C1: QUANTITY SOLD | D1: SELLING PRICE | E1: TOTAL AMOUNT
A2: 45689 | B2: Floor cleaner | C2: 6 | D2: =VLOOKUP(B2,'product price list'!$A:$F,4,FALSE) -> 469.5 | E2: =C2*D2 -> 2817
A3: 45690 | B3: bleaching powder | C3: 19 | D3: =VLOOKUP(B3,'product price list'!$A:$F,4,FALSE) -> 289.5 | E3: =C3*D3 -> 5500.5
A4: 45691 | B4: glass cleaner | C4: 7 | D4: =VLOOKUP(B4,'product price list'!$A:$F,4,FALSE) -> 243 | E4: =C4*D4 -> 1701
A5: 45692 | B5: Naoh | C5: 15 | D5: =VLOOKUP(B5,'product price list'!$A:$F,4,FALSE) -> 601.5 | E5: =C5*D5 -> 9022.5
A6: 45693 | B6: sodium hypochloride | C6: 20 | D6: =VLOOKUP(B6,'product price list'!$A:$F,4,FALSE) -> 165 | E6: =C6*D6 -> 3300
A7: 45694 | B7: handwash | C7: 5 | D7: =VLOOKUP(B7,'product price list'!$A:$F,4,FALSE) -> 601.5 | E7: =C7*D7 -> 3007.5
A8: 45695 | B8: room freshner | C8: 17 | D8: =VLOOKUP(B8,'product price list'!$A:$F,4,FALSE) -> 561 | E8: =C8*D8 -> 9537
A9: 45696 | B9: sanitary cubes | C9: 11 | D9: =VLOOKUP(B9,'product price list'!$A:$F,4,FALSE) -> 373.5 | E9: =C9*D9 -> 4108.5
A10: 45697 | B10: napthalene balls | C10: 3 | D10: =VLOOKUP(B10,'product price list'!$A:$F,4,FALSE) -> 475.5 | E10: =C10*D10 -> 1426.5
A11: 45698 | B11: tissue packs | C11: 12 | D11: =VLOOKUP(B11,'product price list'!$A:$F,4,FALSE) -> 735 | E11: =C11*D11 -> 8820
A12: 45699 | B12: napkins | C12: 10 | D12: =VLOOKUP(B12,'product price list'!$A:$F,4,FALSE) -> 313.5 | E12: =C12*D12 -> 3135
A13: 45700 | B13: mop | C13: 9 | D13: =VLOOKUP(B13,'product price list'!$A:$F,4,FALSE) -> 727.5 | E13: =C13*D13 -> 6547.5
... A20: 45707 | B20: detergent | C20: 13 | D20: =VLOOKUP(B20,'product price list'!$A:$F,4,FALSE) -> 631.5 | E20: =C20*D20 -> 8209.5

Sheet DASHBOARD
A3: Row Labels | B3: Sum of TOTAL AMOUNT
A4: aromas | B4: 544.5
A5: bleaching powder | B5: 5500.5
A6: broom | B6: 5250
A7: detergent | B7: 8209.5
A8: Floor cleaner | B8: 2817
A9: glass cleaner | B9: 1701
A10: handwash | B10: 3007.5
A11: mop | B11: 6547.5
A12: Naoh | B12: 9022.5
A13: napkins | B13: 3135
A14: napthalene balls | B14: 1426.5
A15: oil remover | B15: 2116.5
... A23: Grand Total | B23: 92218.5
